{
  "fetchedAt": "2026-02-20T00:45:39.718Z",
  "region": "eu",
  "count": 4,
  "events": [
    {
      "event_id": "1032f6acddd302f1420db879d292c575",
      "start": "2026-02-20T16:30:00Z",
      "player1": "Andrey Rublev",
      "player2": "Carlos Alcaraz",
      "odds1": 5.84,
      "odds2": 1.15,
      "prob1": "0.1645",
      "prob2": "0.8355",
      "bookmaker": "1xBet",
      "sport_key": "tennis_atp_qatar_open",
      "region": "eu"
    },
    {
      "event_id": "6c1065a33cf8a9c84c32440aa214eb4e",
      "start": "2026-02-20T18:00:00Z",
      "player1": "Arthur Fils",
      "player2": "Jakub Mensik",
      "odds1": 2.16,
      "odds2": 1.73,
      "prob1": "0.4447",
      "prob2": "0.5553",
      "bookmaker": "1xBet",
      "sport_key": "tennis_atp_qatar_open",
      "region": "eu"
    },
    {
      "event_id": "ef71b448ed562cac279ebbd252fd461d",
      "start": "2026-02-20T13:00:00Z",
      "player1": "Amanda Anisimova",
      "player2": "Jessica Pegula",
      "odds1": 2.3,
      "odds2": 1.65,
      "prob1": "0.4177",
      "prob2": "0.5823",
      "bookmaker": "1xBet",
      "sport_key": "tennis_wta_dubai",
      "region": "eu"
    },
    {
      "event_id": "2e87e9af07a4f23c989889b10195dbe7",
      "start": "2026-02-20T15:00:00Z",
      "player1": "Coco Gauff",
      "player2": "Elina Svitolina",
      "odds1": 1.7,
      "odds2": 2.21,
      "prob1": "0.5652",
      "prob2": "0.4348",
      "bookmaker": "1xBet",
      "sport_key": "tennis_wta_dubai",
      "region": "eu"
    }
  ]
}