{
  "fetchedAt": "2026-06-29T01:18:30.070Z",
  "region": "eu",
  "count": 127,
  "events": [
    {
      "event_id": "358d9f8f061afe1f32bc74d63fd80a18",
      "start": "2026-06-29T10:00:00Z",
      "player1": "Aleksandar Kovacevic",
      "player2": "Botic van de Zandschulp",
      "odds1": 2.5,
      "odds2": 1.52,
      "prob1": "0.3781",
      "prob2": "0.6219",
      "bookmaker": "Unibet (FR)",
      "sport_key": "tennis_atp_wimbledon",
      "region": "eu"
    },
    {
      "event_id": "85318dc3ac6a4d71ba495e169a98a0e2",
      "start": "2026-06-29T10:00:00Z",
      "player1": "Aleksandar Vukic",
      "player2": "Jenson Brooksby",
      "odds1": 2.95,
      "odds2": 1.47,
      "prob1": "0.3326",
      "prob2": "0.6674",
      "bookmaker": "1xBet",
      "sport_key": "tennis_atp_wimbledon",
      "region": "eu"
    },
    {
      "event_id": "2118e17ef47c533ba58f35e27d165359",
      "start": "2026-06-29T10:00:00Z",
      "player1": "Andrey Rublev",
      "player2": "Roman Safiullin",
      "odds1": 1.49,
      "odds2": 2.65,
      "prob1": "0.6401",
      "prob2": "0.3599",
      "bookmaker": "MyBookie.ag",
      "sport_key": "tennis_atp_wimbledon",
      "region": "eu"
    },
    {
      "event_id": "a906a642efaf305fcae90cf8324938cf",
      "start": "2026-06-29T10:00:00Z",
      "player1": "Dalibor Svrcina",
      "player2": "Learner Tien",
      "odds1": 7,
      "odds2": 1.1,
      "prob1": "0.1358",
      "prob2": "0.8642",
      "bookmaker": "Unibet (NL)",
      "sport_key": "tennis_atp_wimbledon",
      "region": "eu"
    },
    {
      "event_id": "2af6193491a1eaeeba23d9b48c069d29",
      "start": "2026-06-29T10:00:00Z",
      "player1": "Denis Shapovalov",
      "player2": "Pablo Carreno Busta",
      "odds1": 1.33,
      "odds2": 3.3,
      "prob1": "0.7127",
      "prob2": "0.2873",
      "bookmaker": "Unibet (NL)",
      "sport_key": "tennis_atp_wimbledon",
      "region": "eu"
    },
    {
      "event_id": "81a7afb323fe95aec4531fb018ca024d",
      "start": "2026-06-29T10:00:00Z",
      "player1": "Emilio Nava",
      "player2": "Ignacio Buse",
      "odds1": 2.12,
      "odds2": 1.72,
      "prob1": "0.4479",
      "prob2": "0.5521",
      "bookmaker": "Unibet (NL)",
      "sport_key": "tennis_atp_wimbledon",
      "region": "eu"
    },
    {
      "event_id": "6e402c18521cc5c383d4efc5483635a6",
      "start": "2026-06-29T10:00:00Z",
      "player1": "Felix Gill",
      "player2": "Rafael Jodar",
      "odds1": 4.87,
      "odds2": 1.16,
      "prob1": "0.1924",
      "prob2": "0.8076",
      "bookmaker": "Nordic Bet",
      "sport_key": "tennis_atp_wimbledon",
      "region": "eu"
    },
    {
      "event_id": "24437f0313581ed4096a6bdf264b65bc",
      "start": "2026-06-29T10:00:00Z",
      "player1": "Luca Van Assche",
      "player2": "Marton Fucsovics",
      "odds1": 3,
      "odds2": 1.37,
      "prob1": "0.3135",
      "prob2": "0.6865",
      "bookmaker": "Unibet (FR)",
      "sport_key": "tennis_atp_wimbledon",
      "region": "eu"
    },
    {
      "event_id": "7cfbcb8496407d13034b29b455f88b40",
      "start": "2026-06-29T10:00:00Z",
      "player1": "Marco Trungelliti",
      "player2": "Martin Damm Jr.",
      "odds1": 4.35,
      "odds2": 1.21,
      "prob1": "0.2176",
      "prob2": "0.7824",
      "bookmaker": "Unibet (NL)",
      "sport_key": "tennis_atp_wimbledon",
      "region": "eu"
    },
    {
      "event_id": "91d13ab92f0444ff5b57c0bb347ba26b",
      "start": "2026-06-29T10:00:00Z",
      "player1": "Max Basing",
      "player2": "Shintaro Mochizuki",
      "odds1": 3.1,
      "odds2": 1.47,
      "prob1": "0.3217",
      "prob2": "0.6783",
      "bookmaker": "Betfair",
      "sport_key": "tennis_atp_wimbledon",
      "region": "eu"
    },
    {
      "event_id": "53b0d7fe180b9254ce15cbca0ad73acb",
      "start": "2026-06-29T11:10:00Z",
      "player1": "Alexandre Muller",
      "player2": "Tommy Paul",
      "odds1": 13,
      "odds2": 1.02,
      "prob1": "0.0728",
      "prob2": "0.9272",
      "bookmaker": "888sport",
      "sport_key": "tennis_atp_wimbledon",
      "region": "eu"
    },
    {
      "event_id": "35090f59026ece4c7ffb98c0066d7ad8",
      "start": "2026-06-29T11:10:00Z",
      "player1": "Cameron Norrie",
      "player2": "Michael Zheng",
      "odds1": 1.61,
      "odds2": 2.32,
      "prob1": "0.5903",
      "prob2": "0.4097",
      "bookmaker": "Unibet (NL)",
      "sport_key": "tennis_atp_wimbledon",
      "region": "eu"
    },
    {
      "event_id": "9fd8a8357bfa58b092f899d246021ea6",
      "start": "2026-06-29T11:40:00Z",
      "player1": "Camilo Ugo Carabelli",
      "player2": "Daniel Merida Aguilar",
      "odds1": 1.94,
      "odds2": 1.85,
      "prob1": "0.4881",
      "prob2": "0.5119",
      "bookmaker": "Unibet (NL)",
      "sport_key": "tennis_atp_wimbledon",
      "region": "eu"
    },
    {
      "event_id": "f4fda566e17927780cfdff7db18e2a81",
      "start": "2026-06-29T11:40:00Z",
      "player1": "Casper Ruud",
      "player2": "Hubert Hurkacz",
      "odds1": 2.65,
      "odds2": 1.46,
      "prob1": "0.3552",
      "prob2": "0.6448",
      "bookmaker": "Unibet (FR)",
      "sport_key": "tennis_atp_wimbledon",
      "region": "eu"
    },
    {
      "event_id": "1e236c7f0ccd5b912738250955aa804f",
      "start": "2026-06-29T11:40:00Z",
      "player1": "Hamad Medjedovic",
      "player2": "Sebastian Ofner",
      "odds1": 1.44,
      "odds2": 2.78,
      "prob1": "0.6588",
      "prob2": "0.3412",
      "bookmaker": "Marathon Bet",
      "sport_key": "tennis_atp_wimbledon",
      "region": "eu"
    },
    {
      "event_id": "580a29d7179ba84bc37aa5419f2b5890",
      "start": "2026-06-29T11:40:00Z",
      "player1": "Hugo Gaston",
      "player2": "Stefanos Tsitsipas",
      "odds1": 2.85,
      "odds2": 1.43,
      "prob1": "0.3341",
      "prob2": "0.6659",
      "bookmaker": "Unibet (NL)",
      "sport_key": "tennis_atp_wimbledon",
      "region": "eu"
    },
    {
      "event_id": "32c9d5eb4778378aec022519a0e31702",
      "start": "2026-06-29T11:40:00Z",
      "player1": "Martin Landaluce",
      "player2": "Soonwoo Kwon",
      "odds1": 1.58,
      "odds2": 2.58,
      "prob1": "0.6202",
      "prob2": "0.3798",
      "bookmaker": "1xBet",
      "sport_key": "tennis_atp_wimbledon",
      "region": "eu"
    },
    {
      "event_id": "c561667371bd2ea3fa083b0ffd6defaa",
      "start": "2026-06-29T11:40:00Z",
      "player1": "Nuno Borges",
      "player2": "Tristan Boyer",
      "odds1": 1.32,
      "odds2": 3.4,
      "prob1": "0.7203",
      "prob2": "0.2797",
      "bookmaker": "Unibet (NL)",
      "sport_key": "tennis_atp_wimbledon",
      "region": "eu"
    },
    {
      "event_id": "9c197a6a36fd1d26beeb13fab6c084f9",
      "start": "2026-06-29T12:00:00Z",
      "player1": "Arthur Rinderknech",
      "player2": "Oliver Tarvet",
      "odds1": 1.74,
      "odds2": 2.08,
      "prob1": "0.5445",
      "prob2": "0.4555",
      "bookmaker": "Unibet (NL)",
      "sport_key": "tennis_atp_wimbledon",
      "region": "eu"
    },
    {
      "event_id": "bccd57db28819aad77c423add704c9bc",
      "start": "2026-06-29T12:20:00Z",
      "player1": "Adam Walton",
      "player2": "Dino Prizmic",
      "odds1": 2.3,
      "odds2": 1.6,
      "prob1": "0.4103",
      "prob2": "0.5897",
      "bookmaker": "Unibet (FR)",
      "sport_key": "tennis_atp_wimbledon",
      "region": "eu"
    },
    {
      "event_id": "0e2d2738b36d452faae8d24caa13a7c5",
      "start": "2026-06-29T12:30:00Z",
      "player1": "Jannik Sinner",
      "player2": "Miomir Kecmanovic",
      "odds1": 1,
      "odds2": 17.25,
      "prob1": "0.9452",
      "prob2": "0.0548",
      "bookmaker": "Marathon Bet",
      "sport_key": "tennis_atp_wimbledon",
      "region": "eu"
    },
    {
      "event_id": "1068d5b1ea5defa8627fba4b0edec622",
      "start": "2026-06-29T12:50:00Z",
      "player1": "Adolfo Daniel Vallejo",
      "player2": "Nicolas Mejia",
      "odds1": 1.71,
      "odds2": 2.38,
      "prob1": "0.5819",
      "prob2": "0.4181",
      "bookmaker": "Betfair",
      "sport_key": "tennis_atp_wimbledon",
      "region": "eu"
    },
    {
      "event_id": "beb90503058a173462df0b15039b6ce0",
      "start": "2026-06-29T12:50:00Z",
      "player1": "Alexander Shevchenko",
      "player2": "Felix Auger-Aliassime",
      "odds1": 13,
      "odds2": 1.02,
      "prob1": "0.0728",
      "prob2": "0.9272",
      "bookmaker": "Unibet (FR)",
      "sport_key": "tennis_atp_wimbledon",
      "region": "eu"
    },
    {
      "event_id": "accbf9acb0b25cf8764f18f0e9bbae2f",
      "start": "2026-06-29T12:50:00Z",
      "player1": "Fabian Marozsan",
      "player2": "Thiago Agustin Tirante",
      "odds1": 1.44,
      "odds2": 3.04,
      "prob1": "0.6786",
      "prob2": "0.3214",
      "bookmaker": "1xBet",
      "sport_key": "tennis_atp_wimbledon",
      "region": "eu"
    },
    {
      "event_id": "5892024d4ed6401503435d99df986404",
      "start": "2026-06-29T12:50:00Z",
      "player1": "Joao Fonseca",
      "player2": "Roberto Bautista Agut",
      "odds1": 1.18,
      "odds2": 4.65,
      "prob1": "0.7976",
      "prob2": "0.2024",
      "bookmaker": "Unibet (FR)",
      "sport_key": "tennis_atp_wimbledon",
      "region": "eu"
    },
    {
      "event_id": "68ba4da7fda72170ec9204bd16e38485",
      "start": "2026-06-29T13:10:00Z",
      "player1": "Daniil Medvedev",
      "player2": "Marin Cilic",
      "odds1": 1.33,
      "odds2": 3.3,
      "prob1": "0.7127",
      "prob2": "0.2873",
      "bookmaker": "Unibet (NL)",
      "sport_key": "tennis_atp_wimbledon",
      "region": "eu"
    },
    {
      "event_id": "2db3ab0bc3167d0e2dc13fc5f4be8a8e",
      "start": "2026-06-29T13:10:00Z",
      "player1": "Jan-Lennard Struff",
      "player2": "Sebastian Baez",
      "odds1": 1.38,
      "odds2": 3,
      "prob1": "0.6849",
      "prob2": "0.3151",
      "bookmaker": "Unibet (FR)",
      "sport_key": "tennis_atp_wimbledon",
      "region": "eu"
    },
    {
      "event_id": "320fd6d02bf1479455f689e7e8e32652",
      "start": "2026-06-29T14:00:00Z",
      "player1": "Alejandro Davidovich Fokina",
      "player2": "Juan Manuel Cerundolo",
      "odds1": 1.28,
      "odds2": 3.99,
      "prob1": "0.7571",
      "prob2": "0.2429",
      "bookmaker": "Pinnacle",
      "sport_key": "tennis_atp_wimbledon",
      "region": "eu"
    },
    {
      "event_id": "69332957db75f96119b6693f1d3e7972",
      "start": "2026-06-29T14:00:00Z",
      "player1": "Ethan Quinn",
      "player2": "Luciano Darderi",
      "odds1": 1.65,
      "odds2": 2.36,
      "prob1": "0.5885",
      "prob2": "0.4115",
      "bookmaker": "Pinnacle",
      "sport_key": "tennis_atp_wimbledon",
      "region": "eu"
    },
    {
      "event_id": "c578da64810d91a5395285c9ec1e5d26",
      "start": "2026-06-29T14:00:00Z",
      "player1": "Jesper De Jong",
      "player2": "Rinky Hijikata",
      "odds1": 3.25,
      "odds2": 1.34,
      "prob1": "0.2919",
      "prob2": "0.7081",
      "bookmaker": "Unibet (NL)",
      "sport_key": "tennis_atp_wimbledon",
      "region": "eu"
    },
    {
      "event_id": "88cee7b8ee8e5d8e9d6d864e8d20b236",
      "start": "2026-06-29T15:20:00Z",
      "player1": "Novak Djokovic",
      "player2": "Wu Yibing",
      "odds1": 1.04,
      "odds2": 17,
      "prob1": "0.9424",
      "prob2": "0.0576",
      "bookmaker": "1xBet",
      "sport_key": "tennis_atp_wimbledon",
      "region": "eu"
    },
    {
      "event_id": "e9f9c481cc21d1a81bc66eb5a280e6ba",
      "start": "2026-06-29T16:00:00Z",
      "player1": "Brandon Nakashima",
      "player2": "Jack Pinnington Jones",
      "odds1": 1.26,
      "odds2": 3.9,
      "prob1": "0.7558",
      "prob2": "0.2442",
      "bookmaker": "Unibet (NL)",
      "sport_key": "tennis_atp_wimbledon",
      "region": "eu"
    },
    {
      "event_id": "1f461af14cf88f5bb39b82541e8f7a8c",
      "start": "2026-06-30T09:00:00Z",
      "player1": "Alex Molcan",
      "player2": "Daniel Altmaier",
      "odds1": 2,
      "odds2": 1.89,
      "prob1": "0.4859",
      "prob2": "0.5141",
      "bookmaker": "Pinnacle",
      "sport_key": "tennis_atp_wimbledon",
      "region": "eu"
    },
    {
      "event_id": "48c25244147846976df612a9a36e7867",
      "start": "2026-06-30T09:00:00Z",
      "player1": "Alexander Blockx",
      "player2": "Alexander Zverev",
      "odds1": 7.8,
      "odds2": 1.07,
      "prob1": "0.1206",
      "prob2": "0.8794",
      "bookmaker": "Tipico",
      "sport_key": "tennis_atp_wimbledon",
      "region": "eu"
    },
    {
      "event_id": "cf2ea8e6f0ab96ed5970b0f09a464db6",
      "start": "2026-06-30T09:00:00Z",
      "player1": "Arthur Fils",
      "player2": "Raphael Collignon",
      "odds1": 1.71,
      "odds2": 2.26,
      "prob1": "0.5693",
      "prob2": "0.4307",
      "bookmaker": "Pinnacle",
      "sport_key": "tennis_atp_wimbledon",
      "region": "eu"
    },
    {
      "event_id": "3738018d9203149afd4afebc5ac08b32",
      "start": "2026-06-30T09:00:00Z",
      "player1": "Matteo Berrettini",
      "player2": "Stan Wawrinka",
      "odds1": 1.3,
      "odds2": 3.88,
      "prob1": "0.7490",
      "prob2": "0.2510",
      "bookmaker": "Pinnacle",
      "sport_key": "tennis_atp_wimbledon",
      "region": "eu"
    },
    {
      "event_id": "804a341f757c8a347d3f786fd8870aa5",
      "start": "2026-06-30T09:00:00Z",
      "player1": "Ugo Humbert",
      "player2": "Zizou Bergs",
      "odds1": 1.57,
      "odds2": 2.55,
      "prob1": "0.6189",
      "prob2": "0.3811",
      "bookmaker": "Pinnacle",
      "sport_key": "tennis_atp_wimbledon",
      "region": "eu"
    },
    {
      "event_id": "b504b767081c8cfde1fb8fd2f36016cb",
      "start": "2026-06-30T10:00:00Z",
      "player1": "Adrian Mannarino",
      "player2": "Titouan Droguet",
      "odds1": 1.56,
      "odds2": 2.42,
      "prob1": "0.6080",
      "prob2": "0.3920",
      "bookmaker": "Marathon Bet",
      "sport_key": "tennis_atp_wimbledon",
      "region": "eu"
    },
    {
      "event_id": "24a90ba03322c9d26e5f654e072992b8",
      "start": "2026-06-30T10:00:00Z",
      "player1": "Alejandro Tabilo",
      "player2": "Kamil Majchrzak",
      "odds1": 2.75,
      "odds2": 1.44,
      "prob1": "0.3437",
      "prob2": "0.6563",
      "bookmaker": "Unibet (FR)",
      "sport_key": "tennis_atp_wimbledon",
      "region": "eu"
    },
    {
      "event_id": "2ba367a0a2de0261300b51574f55dde7",
      "start": "2026-06-30T10:00:00Z",
      "player1": "Giovanni Mpetshi Perricard",
      "player2": "Yannick Hanfmann",
      "odds1": 1.65,
      "odds2": 2.25,
      "prob1": "0.5769",
      "prob2": "0.4231",
      "bookmaker": "Unibet (NL)",
      "sport_key": "tennis_atp_wimbledon",
      "region": "eu"
    },
    {
      "event_id": "e9717b439a749ca3371aff2a287da57b",
      "start": "2026-06-30T10:00:00Z",
      "player1": "Harry Wendelken",
      "player2": "Valentin Royer",
      "odds1": 2.13,
      "odds2": 1.71,
      "prob1": "0.4453",
      "prob2": "0.5547",
      "bookmaker": "Marathon Bet",
      "sport_key": "tennis_atp_wimbledon",
      "region": "eu"
    },
    {
      "event_id": "8752814a29f6219f5ef0383afc948739",
      "start": "2026-06-30T10:00:00Z",
      "player1": "Jaime Faria",
      "player2": "Sho Shimabukuro",
      "odds1": 1.95,
      "odds2": 1.85,
      "prob1": "0.4868",
      "prob2": "0.5132",
      "bookmaker": "Unibet (NL)",
      "sport_key": "tennis_atp_wimbledon",
      "region": "eu"
    },
    {
      "event_id": "14e1451c778870ff2953df9faeea10ec",
      "start": "2026-06-30T11:10:00Z",
      "player1": "Alex Michelsen",
      "player2": "Jacob Fearnley",
      "odds1": 1.74,
      "odds2": 2.04,
      "prob1": "0.5397",
      "prob2": "0.4603",
      "bookmaker": "PMU (FR)",
      "sport_key": "tennis_atp_wimbledon",
      "region": "eu"
    },
    {
      "event_id": "b2957a20a6add0bae2029fc52472853b",
      "start": "2026-06-30T11:10:00Z",
      "player1": "Alex de Minaur",
      "player2": "Roman Andres Burruchaga",
      "odds1": 1.04,
      "odds2": 11,
      "prob1": "0.9136",
      "prob2": "0.0864",
      "bookmaker": "Unibet (NL)",
      "sport_key": "tennis_atp_wimbledon",
      "region": "eu"
    },
    {
      "event_id": "1a76e2740082417247d02923fdbf8dd1",
      "start": "2026-06-30T11:10:00Z",
      "player1": "Alexander Bublik",
      "player2": "Thanasi Kokkinakis",
      "odds1": 1.38,
      "odds2": 3.05,
      "prob1": "0.6885",
      "prob2": "0.3115",
      "bookmaker": "Unibet (NL)",
      "sport_key": "tennis_atp_wimbledon",
      "region": "eu"
    },
    {
      "event_id": "bdd4cc16157f42d8f1c91c2b37c8c9ba",
      "start": "2026-06-30T11:10:00Z",
      "player1": "Arthur Fery",
      "player2": "Damir Dzumhur",
      "odds1": 1.24,
      "odds2": 4,
      "prob1": "0.7634",
      "prob2": "0.2366",
      "bookmaker": "Unibet (NL)",
      "sport_key": "tennis_atp_wimbledon",
      "region": "eu"
    },
    {
      "event_id": "11cb4a8d64c55c75fbbf745ae653a21f",
      "start": "2026-06-30T11:10:00Z",
      "player1": "Ben Shelton",
      "player2": "Otto Virtanen",
      "odds1": 1.31,
      "odds2": 3.9,
      "prob1": "0.7486",
      "prob2": "0.2514",
      "bookmaker": "1xBet",
      "sport_key": "tennis_atp_wimbledon",
      "region": "eu"
    },
    {
      "event_id": "a781545b6be54ba4f37eea8f21ed6695",
      "start": "2026-06-30T11:10:00Z",
      "player1": "Billy Harris",
      "player2": "Karen Khachanov",
      "odds1": 3.64,
      "odds2": 1.34,
      "prob1": "0.2691",
      "prob2": "0.7309",
      "bookmaker": "1xBet",
      "sport_key": "tennis_atp_wimbledon",
      "region": "eu"
    },
    {
      "event_id": "ac6f094b413a84d452192b5b4fb636a4",
      "start": "2026-06-30T11:10:00Z",
      "player1": "Kyrian Jacquet",
      "player2": "Vilius Gaubas",
      "odds1": 1.42,
      "odds2": 2.88,
      "prob1": "0.6698",
      "prob2": "0.3302",
      "bookmaker": "Unibet (NL)",
      "sport_key": "tennis_atp_wimbledon",
      "region": "eu"
    },
    {
      "event_id": "4579733c9a884ba46e917832c215723c",
      "start": "2026-06-30T11:10:00Z",
      "player1": "Matteo Arnaldi",
      "player2": "Quentin Halys",
      "odds1": 1.97,
      "odds2": 1.82,
      "prob1": "0.4802",
      "prob2": "0.5198",
      "bookmaker": "Unibet (NL)",
      "sport_key": "tennis_atp_wimbledon",
      "region": "eu"
    },
    {
      "event_id": "cf27d2437d51cc92259b62ce0b8d7c23",
      "start": "2026-06-30T11:10:00Z",
      "player1": "Mattia Bellucci",
      "player2": "Zachary Svajda",
      "odds1": 1.71,
      "odds2": 2.07,
      "prob1": "0.5476",
      "prob2": "0.4524",
      "bookmaker": "PMU (FR)",
      "sport_key": "tennis_atp_wimbledon",
      "region": "eu"
    },
    {
      "event_id": "4c10f9c86780b761fa8b22928e0534f9",
      "start": "2026-06-30T11:40:00Z",
      "player1": "Benjamin Bonzi",
      "player2": "Gabriel Diallo",
      "odds1": 1.93,
      "odds2": 1.87,
      "prob1": "0.4921",
      "prob2": "0.5079",
      "bookmaker": "Unibet (NL)",
      "sport_key": "tennis_atp_wimbledon",
      "region": "eu"
    },
    {
      "event_id": "9790547605ef70511264c7e5bb6122e9",
      "start": "2026-06-30T11:40:00Z",
      "player1": "Francisco Cerundolo",
      "player2": "Jaume Munar",
      "odds1": 1.28,
      "odds2": 4.1,
      "prob1": "0.7621",
      "prob2": "0.2379",
      "bookmaker": "Betfair",
      "sport_key": "tennis_atp_wimbledon",
      "region": "eu"
    },
    {
      "event_id": "289a97fe64fe86154553f9dfdde13bcb",
      "start": "2026-06-30T12:50:00Z",
      "player1": "Corentin Moutet",
      "player2": "Marcos Giron",
      "odds1": 2,
      "odds2": 1.81,
      "prob1": "0.4751",
      "prob2": "0.5249",
      "bookmaker": "Unibet (NL)",
      "sport_key": "tennis_atp_wimbledon",
      "region": "eu"
    },
    {
      "event_id": "d85a15638614401bf53f2f4105ebea99",
      "start": "2026-06-30T12:50:00Z",
      "player1": "Dane Sweeny",
      "player2": "Grigor Dimitrov",
      "odds1": 3.95,
      "odds2": 1.25,
      "prob1": "0.2404",
      "prob2": "0.7596",
      "bookmaker": "Unibet (NL)",
      "sport_key": "tennis_atp_wimbledon",
      "region": "eu"
    },
    {
      "event_id": "5ebcde4d1cf57d0a3b9b99c4a40b00a1",
      "start": "2026-06-30T12:50:00Z",
      "player1": "Jakub Mensik",
      "player2": "Toby Samuel",
      "odds1": 1.38,
      "odds2": 3,
      "prob1": "0.6849",
      "prob2": "0.3151",
      "bookmaker": "Unibet (NL)",
      "sport_key": "tennis_atp_wimbledon",
      "region": "eu"
    },
    {
      "event_id": "6f5afd8b1147cc48f757ed20f14464d3",
      "start": "2026-06-30T12:50:00Z",
      "player1": "Lorenzo Sonego",
      "player2": "Tomas Martin Etcheverry",
      "odds1": 1.76,
      "odds2": 2,
      "prob1": "0.5319",
      "prob2": "0.4681",
      "bookmaker": "PMU (FR)",
      "sport_key": "tennis_atp_wimbledon",
      "region": "eu"
    },
    {
      "event_id": "fb65964d02c99ad637e0a48d3afa66ad",
      "start": "2026-06-30T12:50:00Z",
      "player1": "Mackenzie McDonald",
      "player2": "Patrick Kypson",
      "odds1": 1.33,
      "odds2": 3.2,
      "prob1": "0.7064",
      "prob2": "0.2936",
      "bookmaker": "Tipico",
      "sport_key": "tennis_atp_wimbledon",
      "region": "eu"
    },
    {
      "event_id": "2953d0eade4d5062d058efbc9e7b1458",
      "start": "2026-06-30T13:40:00Z",
      "player1": "Jack Draper",
      "player2": "Taylor Fritz",
      "odds1": 2.38,
      "odds2": 1.57,
      "prob1": "0.3975",
      "prob2": "0.6025",
      "bookmaker": "Unibet (NL)",
      "sport_key": "tennis_atp_wimbledon",
      "region": "eu"
    },
    {
      "event_id": "8db5bd8b78df6f2384e180511464bc2f",
      "start": "2026-06-30T14:00:00Z",
      "player1": "Flavio Cobolli",
      "player2": "Mariano Navone",
      "odds1": 1.25,
      "odds2": 3.95,
      "prob1": "0.7596",
      "prob2": "0.2404",
      "bookmaker": "Unibet (NL)",
      "sport_key": "tennis_atp_wimbledon",
      "region": "eu"
    },
    {
      "event_id": "be9660c95afe70b298a651e964aaebef",
      "start": "2026-06-30T14:00:00Z",
      "player1": "Frances Tiafoe",
      "player2": "Terence Atmane",
      "odds1": 1.23,
      "odds2": 4.15,
      "prob1": "0.7714",
      "prob2": "0.2286",
      "bookmaker": "Marathon Bet",
      "sport_key": "tennis_atp_wimbledon",
      "region": "eu"
    },
    {
      "event_id": "90cdc9029092a0350246b5c70f7bc4c0",
      "start": "2026-06-30T14:00:00Z",
      "player1": "James Duckworth",
      "player2": "Tallon Griekspoor",
      "odds1": 2.85,
      "odds2": 1.42,
      "prob1": "0.3326",
      "prob2": "0.6674",
      "bookmaker": "Unibet (NL)",
      "sport_key": "tennis_atp_wimbledon",
      "region": "eu"
    },
    {
      "event_id": "8e6925fad6057e0590572c11cf78188d",
      "start": "2026-06-30T14:00:00Z",
      "player1": "Jan Choinski",
      "player2": "Vit Kopriva",
      "odds1": 2.3,
      "odds2": 1.61,
      "prob1": "0.4118",
      "prob2": "0.5882",
      "bookmaker": "Unibet (NL)",
      "sport_key": "tennis_atp_wimbledon",
      "region": "eu"
    },
    {
      "event_id": "bf95b92b1856ff46a8bd2b89958e4657",
      "start": "2026-06-30T14:50:00Z",
      "player1": "Alexei Popyrin",
      "player2": "Jiri Lehecka",
      "odds1": 3.55,
      "odds2": 1.3,
      "prob1": "0.2680",
      "prob2": "0.7320",
      "bookmaker": "Unibet (NL)",
      "sport_key": "tennis_atp_wimbledon",
      "region": "eu"
    },
    {
      "event_id": "e19c363952aa0ccb9aa59102ccf6cd0f",
      "start": "2026-06-29T10:00:00Z",
      "player1": "Belinda Bencic",
      "player2": "Mika Stojsavljevic",
      "odds1": 1.1,
      "odds2": 7.29,
      "prob1": "0.8689",
      "prob2": "0.1311",
      "bookmaker": "Pinnacle",
      "sport_key": "tennis_wta_wimbledon",
      "region": "eu"
    },
    {
      "event_id": "818f2131f55ad9fca895c5bd3b883155",
      "start": "2026-06-29T10:00:00Z",
      "player1": "Darja Vidmanova",
      "player2": "Jessica Pegula",
      "odds1": 11.51,
      "odds2": 1.05,
      "prob1": "0.0836",
      "prob2": "0.9164",
      "bookmaker": "Pinnacle",
      "sport_key": "tennis_wta_wimbledon",
      "region": "eu"
    },
    {
      "event_id": "41f10a996e7837136475a6cfc93a9d62",
      "start": "2026-06-29T10:00:00Z",
      "player1": "Iva Jović",
      "player2": "Jaqueline Cristian",
      "odds1": 1.19,
      "odds2": 4.99,
      "prob1": "0.8074",
      "prob2": "0.1926",
      "bookmaker": "Pinnacle",
      "sport_key": "tennis_wta_wimbledon",
      "region": "eu"
    },
    {
      "event_id": "838eca72eaf7aafec47216f69c4dcc68",
      "start": "2026-06-29T10:00:00Z",
      "player1": "Maja Chwalinska",
      "player2": "Mananchaya Sawangkaew",
      "odds1": 1.82,
      "odds2": 2.05,
      "prob1": "0.5297",
      "prob2": "0.4703",
      "bookmaker": "Pinnacle",
      "sport_key": "tennis_wta_wimbledon",
      "region": "eu"
    },
    {
      "event_id": "b0970dfaca2e3b95518ea2737489f865",
      "start": "2026-06-29T10:00:00Z",
      "player1": "Sara Sorribes Tormo",
      "player2": "Victoria Jimenez Kasintseva",
      "odds1": 1.71,
      "odds2": 2.2,
      "prob1": "0.5627",
      "prob2": "0.4373",
      "bookmaker": "Pinnacle",
      "sport_key": "tennis_wta_wimbledon",
      "region": "eu"
    },
    {
      "event_id": "04d8a18bde683ba421b314f188fb5ecd",
      "start": "2026-06-29T12:00:00Z",
      "player1": "Alicia Dudeney",
      "player2": "Alycia Parks",
      "odds1": 2.63,
      "odds2": 1.52,
      "prob1": "0.3663",
      "prob2": "0.6337",
      "bookmaker": "Pinnacle",
      "sport_key": "tennis_wta_wimbledon",
      "region": "eu"
    },
    {
      "event_id": "dc6970a8a67c42061ae7bcd79be77da6",
      "start": "2026-06-29T12:00:00Z",
      "player1": "Ann Li",
      "player2": "Zeynep Sonmez",
      "odds1": 2.08,
      "odds2": 1.79,
      "prob1": "0.4625",
      "prob2": "0.5375",
      "bookmaker": "Pinnacle",
      "sport_key": "tennis_wta_wimbledon",
      "region": "eu"
    },
    {
      "event_id": "84b71750c1817bc7c5ceecc3518fa912",
      "start": "2026-06-29T12:00:00Z",
      "player1": "Bianca Andreescu",
      "player2": "Shuai Zhang",
      "odds1": 1.6,
      "odds2": 2.42,
      "prob1": "0.6020",
      "prob2": "0.3980",
      "bookmaker": "Pinnacle",
      "sport_key": "tennis_wta_wimbledon",
      "region": "eu"
    },
    {
      "event_id": "df20c78f4e7ae0fc445c1d89e7283ec1",
      "start": "2026-06-29T12:00:00Z",
      "player1": "Elisabetta Cocciaretto",
      "player2": "Xinyu Wang",
      "odds1": 2.29,
      "odds2": 1.66,
      "prob1": "0.4203",
      "prob2": "0.5797",
      "bookmaker": "Pinnacle",
      "sport_key": "tennis_wta_wimbledon",
      "region": "eu"
    },
    {
      "event_id": "182a2fa8a4f7a9fe0eafb5a4072df3c0",
      "start": "2026-06-29T12:00:00Z",
      "player1": "Harriet Dart",
      "player2": "Jelena Ostapenko",
      "odds1": 3.83,
      "odds2": 1.29,
      "prob1": "0.2520",
      "prob2": "0.7480",
      "bookmaker": "Pinnacle",
      "sport_key": "tennis_wta_wimbledon",
      "region": "eu"
    },
    {
      "event_id": "39a70eb742ef5a7cc85ccdedd797529c",
      "start": "2026-06-29T12:00:00Z",
      "player1": "Tatjana Maria",
      "player2": "Yulia Putintseva",
      "odds1": 1.46,
      "odds2": 2.84,
      "prob1": "0.6605",
      "prob2": "0.3395",
      "bookmaker": "Pinnacle",
      "sport_key": "tennis_wta_wimbledon",
      "region": "eu"
    },
    {
      "event_id": "50d1ffda1ce68df41ae9ad4cb2e4501c",
      "start": "2026-06-29T14:00:00Z",
      "player1": "Anastasia Zakharova",
      "player2": "Karolina Muchova",
      "odds1": 5.97,
      "odds2": 1.14,
      "prob1": "0.1603",
      "prob2": "0.8397",
      "bookmaker": "Pinnacle",
      "sport_key": "tennis_wta_wimbledon",
      "region": "eu"
    },
    {
      "event_id": "1e80ffcac40f0d69f14cb0b053708926",
      "start": "2026-06-29T14:00:00Z",
      "player1": "Claire Liu",
      "player2": "Hanne Vandewinkel",
      "odds1": 1.7,
      "odds2": 2.22,
      "prob1": "0.5663",
      "prob2": "0.4337",
      "bookmaker": "Pinnacle",
      "sport_key": "tennis_wta_wimbledon",
      "region": "eu"
    },
    {
      "event_id": "1ac6e972773b825b2225a0844b4b3e08",
      "start": "2026-06-29T14:00:00Z",
      "player1": "Daria Kasatkina",
      "player2": "Mingge Xu",
      "odds1": 1.11,
      "odds2": 6.8,
      "prob1": "0.8597",
      "prob2": "0.1403",
      "bookmaker": "Pinnacle",
      "sport_key": "tennis_wta_wimbledon",
      "region": "eu"
    },
    {
      "event_id": "b3df87bc081903f4ad654a6a389e829d",
      "start": "2026-06-29T14:00:00Z",
      "player1": "Elsa Jacquemot",
      "player2": "Naomi Osaka",
      "odds1": 6,
      "odds2": 1.14,
      "prob1": "0.1597",
      "prob2": "0.8403",
      "bookmaker": "Pinnacle",
      "sport_key": "tennis_wta_wimbledon",
      "region": "eu"
    },
    {
      "event_id": "1b492d961a8b1debaed7f8b7fb1f2a5c",
      "start": "2026-06-29T14:00:00Z",
      "player1": "Lanlana Tararudee",
      "player2": "Lilli Tagger",
      "odds1": 2.35,
      "odds2": 1.63,
      "prob1": "0.4095",
      "prob2": "0.5905",
      "bookmaker": "Pinnacle",
      "sport_key": "tennis_wta_wimbledon",
      "region": "eu"
    },
    {
      "event_id": "9b6673cf8f207de28b1432975cfd9143",
      "start": "2026-06-29T14:00:00Z",
      "player1": "McCartney Kessler",
      "player2": "Oleksandra Oliynykova",
      "odds1": 1.13,
      "odds2": 6.3,
      "prob1": "0.8479",
      "prob2": "0.1521",
      "bookmaker": "Pinnacle",
      "sport_key": "tennis_wta_wimbledon",
      "region": "eu"
    },
    {
      "event_id": "ed8ee4f4fe27487ce2a15f95a7aa53b9",
      "start": "2026-06-29T14:00:00Z",
      "player1": "Nikola Bartunkova",
      "player2": "Peyton Stearns",
      "odds1": 1.43,
      "odds2": 2.97,
      "prob1": "0.6750",
      "prob2": "0.3250",
      "bookmaker": "Pinnacle",
      "sport_key": "tennis_wta_wimbledon",
      "region": "eu"
    },
    {
      "event_id": "7ac996de69c01e04168104a1fba06ce0",
      "start": "2026-06-29T14:30:00Z",
      "player1": "Aryna Sabalenka",
      "player2": "Teodora Kostovic",
      "odds1": 1.03,
      "odds2": 16,
      "prob1": "0.9395",
      "prob2": "0.0605",
      "bookmaker": "Winamax (FR)",
      "sport_key": "tennis_wta_wimbledon",
      "region": "eu"
    },
    {
      "event_id": "f19608e8dcc80d08c1f7e482760fb36e",
      "start": "2026-06-29T16:00:00Z",
      "player1": "Anastasia Gasanova",
      "player2": "Emiliana Arango",
      "odds1": 2.12,
      "odds2": 1.77,
      "prob1": "0.4550",
      "prob2": "0.5450",
      "bookmaker": "Pinnacle",
      "sport_key": "tennis_wta_wimbledon",
      "region": "eu"
    },
    {
      "event_id": "e3293906c1e46137a88ebd5981335df2",
      "start": "2026-06-29T16:00:00Z",
      "player1": "Anastasia Potapova",
      "player2": "Jessica Bouzas Maneiro",
      "odds1": 1.68,
      "odds2": 2.26,
      "prob1": "0.5736",
      "prob2": "0.4264",
      "bookmaker": "Pinnacle",
      "sport_key": "tennis_wta_wimbledon",
      "region": "eu"
    },
    {
      "event_id": "440ff391d2ed583aa1fc981714c07f5a",
      "start": "2026-06-29T16:00:00Z",
      "player1": "Anna Bondár",
      "player2": "Solana Sierra",
      "odds1": 2.56,
      "odds2": 1.54,
      "prob1": "0.3756",
      "prob2": "0.6244",
      "bookmaker": "Pinnacle",
      "sport_key": "tennis_wta_wimbledon",
      "region": "eu"
    },
    {
      "event_id": "77a19a539ad3a7f15c1c101f172e816b",
      "start": "2026-06-29T16:00:00Z",
      "player1": "Anna Kalinskaya",
      "player2": "Magdalena Frech",
      "odds1": 1.41,
      "odds2": 3.04,
      "prob1": "0.6831",
      "prob2": "0.3169",
      "bookmaker": "Pinnacle",
      "sport_key": "tennis_wta_wimbledon",
      "region": "eu"
    },
    {
      "event_id": "edd244d5ba779798318bf2b4fd3287e2",
      "start": "2026-06-29T16:00:00Z",
      "player1": "Aoi Ito",
      "player2": "Dayana Yastremska",
      "odds1": 5.19,
      "odds2": 1.18,
      "prob1": "0.1852",
      "prob2": "0.8148",
      "bookmaker": "Pinnacle",
      "sport_key": "tennis_wta_wimbledon",
      "region": "eu"
    },
    {
      "event_id": "c8a7097ba2046699dc788b375052f4be",
      "start": "2026-06-29T16:00:00Z",
      "player1": "Barbora Krejcikova",
      "player2": "Hannah Klugman",
      "odds1": 1.07,
      "odds2": 8.87,
      "prob1": "0.8924",
      "prob2": "0.1076",
      "bookmaker": "Pinnacle",
      "sport_key": "tennis_wta_wimbledon",
      "region": "eu"
    },
    {
      "event_id": "0a263b32bda46bb0c5eacda42b37804c",
      "start": "2026-06-29T16:00:00Z",
      "player1": "Coco Gauff",
      "player2": "Tamara Korpatsch",
      "odds1": 1.03,
      "odds2": 16.08,
      "prob1": "0.9398",
      "prob2": "0.0602",
      "bookmaker": "Pinnacle",
      "sport_key": "tennis_wta_wimbledon",
      "region": "eu"
    },
    {
      "event_id": "71b4c7ce59b5202cb955088bf7ffa1da",
      "start": "2026-06-29T16:00:00Z",
      "player1": "Diane Parry",
      "player2": "Francesca Jones",
      "odds1": 1.3,
      "odds2": 3.72,
      "prob1": "0.7410",
      "prob2": "0.2590",
      "bookmaker": "Pinnacle",
      "sport_key": "tennis_wta_wimbledon",
      "region": "eu"
    },
    {
      "event_id": "98e1d43f797c2b249ee1aff59185f8be",
      "start": "2026-06-29T16:00:00Z",
      "player1": "Ekaterina Alexandrova",
      "player2": "Panna Udvardy",
      "odds1": 1.19,
      "odds2": 5.07,
      "prob1": "0.8099",
      "prob2": "0.1901",
      "bookmaker": "Pinnacle",
      "sport_key": "tennis_wta_wimbledon",
      "region": "eu"
    },
    {
      "event_id": "47e49ba7926715df377410816a0eba9c",
      "start": "2026-06-29T16:00:00Z",
      "player1": "Janice Tjen",
      "player2": "Leylah Fernandez",
      "odds1": 3.15,
      "odds2": 1.39,
      "prob1": "0.3062",
      "prob2": "0.6938",
      "bookmaker": "Pinnacle",
      "sport_key": "tennis_wta_wimbledon",
      "region": "eu"
    },
    {
      "event_id": "9b2ab9994bd18c8335610e4c9bb6cdab",
      "start": "2026-06-29T16:00:00Z",
      "player1": "Katerina Siniakova",
      "player2": "Qinwen Zheng",
      "odds1": 1.72,
      "odds2": 2.19,
      "prob1": "0.5601",
      "prob2": "0.4399",
      "bookmaker": "Pinnacle",
      "sport_key": "tennis_wta_wimbledon",
      "region": "eu"
    },
    {
      "event_id": "dae7bdca845592242ea40af724e5e544",
      "start": "2026-06-29T16:00:00Z",
      "player1": "Magda Linette",
      "player2": "Mirra Andreeva",
      "odds1": 4.89,
      "odds2": 1.2,
      "prob1": "0.1970",
      "prob2": "0.8030",
      "bookmaker": "Pinnacle",
      "sport_key": "tennis_wta_wimbledon",
      "region": "eu"
    },
    {
      "event_id": "893ee653eb667aab038cbff36a04017d",
      "start": "2026-06-30T09:00:00Z",
      "player1": "Ajla Tomljanovic",
      "player2": "Mariam Bolkvadze",
      "odds1": 1.14,
      "odds2": 6.02,
      "prob1": "0.8408",
      "prob2": "0.1592",
      "bookmaker": "Pinnacle",
      "sport_key": "tennis_wta_wimbledon",
      "region": "eu"
    },
    {
      "event_id": "e98ed21d69aca9c7c1a7c5ec524d8473",
      "start": "2026-06-30T09:00:00Z",
      "player1": "Alexandra Eala",
      "player2": "Renata Zarazua",
      "odds1": 1.14,
      "odds2": 6.02,
      "prob1": "0.8408",
      "prob2": "0.1592",
      "bookmaker": "Pinnacle",
      "sport_key": "tennis_wta_wimbledon",
      "region": "eu"
    },
    {
      "event_id": "eb33a85597571453f56df3e4a2130616",
      "start": "2026-06-30T09:00:00Z",
      "player1": "Alina Korneeva",
      "player2": "Kimberly Birrell",
      "odds1": 2.09,
      "odds2": 1.79,
      "prob1": "0.4613",
      "prob2": "0.5387",
      "bookmaker": "Pinnacle",
      "sport_key": "tennis_wta_wimbledon",
      "region": "eu"
    },
    {
      "event_id": "cd8d380ae9f11e06b4c149037ee2eb13",
      "start": "2026-06-30T09:00:00Z",
      "player1": "Anhelina Kalinina",
      "player2": "Kamilla Rakhimova",
      "odds1": 1.57,
      "odds2": 2.49,
      "prob1": "0.6133",
      "prob2": "0.3867",
      "bookmaker": "Pinnacle",
      "sport_key": "tennis_wta_wimbledon",
      "region": "eu"
    },
    {
      "event_id": "1a3a51aef4d24e1269cdc4d48a3c103e",
      "start": "2026-06-30T09:00:00Z",
      "player1": "Ashlyn Krueger",
      "player2": "Donna Vekic",
      "odds1": 2.35,
      "odds2": 1.63,
      "prob1": "0.4095",
      "prob2": "0.5905",
      "bookmaker": "Pinnacle",
      "sport_key": "tennis_wta_wimbledon",
      "region": "eu"
    },
    {
      "event_id": "ebe15c4263a4dea851cbea6c5b75b00c",
      "start": "2026-06-30T09:00:00Z",
      "player1": "Beatriz Haddad Maia",
      "player2": "Maria Timofeeva",
      "odds1": 3.22,
      "odds2": 1.37,
      "prob1": "0.2985",
      "prob2": "0.7015",
      "bookmaker": "Pinnacle",
      "sport_key": "tennis_wta_wimbledon",
      "region": "eu"
    },
    {
      "event_id": "eadcb76fb50be336f548a45fbd958f44",
      "start": "2026-06-30T09:00:00Z",
      "player1": "Caty McNally",
      "player2": "Elena Gabriela Ruse",
      "odds1": 2.21,
      "odds2": 1.71,
      "prob1": "0.4362",
      "prob2": "0.5638",
      "bookmaker": "Pinnacle",
      "sport_key": "tennis_wta_wimbledon",
      "region": "eu"
    },
    {
      "event_id": "44b4669bfb971045e1bac6b117cee39e",
      "start": "2026-06-30T09:00:00Z",
      "player1": "Clara Tauson",
      "player2": "Maria Sakkari",
      "odds1": 1.52,
      "odds2": 2.62,
      "prob1": "0.6329",
      "prob2": "0.3671",
      "bookmaker": "Pinnacle",
      "sport_key": "tennis_wta_wimbledon",
      "region": "eu"
    },
    {
      "event_id": "4a2a79624b915d81f1d3b959641d5043",
      "start": "2026-06-30T09:00:00Z",
      "player1": "Daria Snigur",
      "player2": "Elina Svitolina",
      "odds1": 3.36,
      "odds2": 1.35,
      "prob1": "0.2866",
      "prob2": "0.7134",
      "bookmaker": "Pinnacle",
      "sport_key": "tennis_wta_wimbledon",
      "region": "eu"
    },
    {
      "event_id": "0a8ca1b9359b311b09ac57082392f528",
      "start": "2026-06-30T09:00:00Z",
      "player1": "Diana Shnaider",
      "player2": "Eva Lys",
      "odds1": 1.5,
      "odds2": 2.7,
      "prob1": "0.6429",
      "prob2": "0.3571",
      "bookmaker": "Pinnacle",
      "sport_key": "tennis_wta_wimbledon",
      "region": "eu"
    },
    {
      "event_id": "027b38210232721b66c17a7d6a9063d6",
      "start": "2026-06-30T09:00:00Z",
      "player1": "Elise Mertens",
      "player2": "Laura Siegemund",
      "odds1": 1.31,
      "odds2": 3.61,
      "prob1": "0.7337",
      "prob2": "0.2663",
      "bookmaker": "Pinnacle",
      "sport_key": "tennis_wta_wimbledon",
      "region": "eu"
    },
    {
      "event_id": "c47800f5cd90c057dd3b44cd54c132cd",
      "start": "2026-06-30T09:00:00Z",
      "player1": "Ella Seidel",
      "player2": "Linda Noskova",
      "odds1": 7.07,
      "odds2": 1.11,
      "prob1": "0.1357",
      "prob2": "0.8643",
      "bookmaker": "Pinnacle",
      "sport_key": "tennis_wta_wimbledon",
      "region": "eu"
    },
    {
      "event_id": "5c544a836d5ec20c47a6539767f1952c",
      "start": "2026-06-30T09:00:00Z",
      "player1": "Emma Navarro",
      "player2": "Paula Badosa",
      "odds1": 1.62,
      "odds2": 2.36,
      "prob1": "0.5930",
      "prob2": "0.4070",
      "bookmaker": "Pinnacle",
      "sport_key": "tennis_wta_wimbledon",
      "region": "eu"
    },
    {
      "event_id": "6ad4350f8af91730f0ca127171f3c535",
      "start": "2026-06-30T09:00:00Z",
      "player1": "Iga Swiatek",
      "player2": "Taylor Townsend",
      "odds1": 1.15,
      "odds2": 5.76,
      "prob1": "0.8336",
      "prob2": "0.1664",
      "bookmaker": "Pinnacle",
      "sport_key": "tennis_wta_wimbledon",
      "region": "eu"
    },
    {
      "event_id": "62389581cb3de1566e5285f0dd385f28",
      "start": "2026-06-30T09:00:00Z",
      "player1": "Irina-Camelia Begu",
      "player2": "Katie Swan",
      "odds1": 1.94,
      "odds2": 1.91,
      "prob1": "0.4961",
      "prob2": "0.5039",
      "bookmaker": "Pinnacle",
      "sport_key": "tennis_wta_wimbledon",
      "region": "eu"
    },
    {
      "event_id": "7be2ff9ae0b5a1bb5f5c177f5f12c315",
      "start": "2026-06-30T09:00:00Z",
      "player1": "Iryna Shymanovich",
      "player2": "Viktorija Golubic",
      "odds1": 3.76,
      "odds2": 1.29,
      "prob1": "0.2554",
      "prob2": "0.7446",
      "bookmaker": "Pinnacle",
      "sport_key": "tennis_wta_wimbledon",
      "region": "eu"
    },
    {
      "event_id": "0929860c70b30ee6540f7af87376fabc",
      "start": "2026-06-30T09:00:00Z",
      "player1": "Jasmine Paolini",
      "player2": "Robin Montgomery",
      "odds1": 2.48,
      "odds2": 1.57,
      "prob1": "0.3877",
      "prob2": "0.6123",
      "bookmaker": "Pinnacle",
      "sport_key": "tennis_wta_wimbledon",
      "region": "eu"
    },
    {
      "event_id": "effae0e3093be6a9d77679735984dab3",
      "start": "2026-06-30T09:00:00Z",
      "player1": "Karolina Pliskova",
      "player2": "Tereza Valentova",
      "odds1": 1.78,
      "odds2": 2.1,
      "prob1": "0.5412",
      "prob2": "0.4588",
      "bookmaker": "Pinnacle",
      "sport_key": "tennis_wta_wimbledon",
      "region": "eu"
    },
    {
      "event_id": "ad418491f95a205a1207f1c061536d2b",
      "start": "2026-06-30T09:00:00Z",
      "player1": "Katie Boulter",
      "player2": "Tyra Caterina Grant",
      "odds1": 1.37,
      "odds2": 3.23,
      "prob1": "0.7022",
      "prob2": "0.2978",
      "bookmaker": "Pinnacle",
      "sport_key": "tennis_wta_wimbledon",
      "region": "eu"
    },
    {
      "event_id": "2eb222f66f91ea92e266cfefe3c86879",
      "start": "2026-06-30T09:00:00Z",
      "player1": "Kayla Day",
      "player2": "Madison Keys",
      "odds1": 9.16,
      "odds2": 1.07,
      "prob1": "0.1046",
      "prob2": "0.8954",
      "bookmaker": "Pinnacle",
      "sport_key": "tennis_wta_wimbledon",
      "region": "eu"
    },
    {
      "event_id": "09384620e7201c595739307dddc7c68a",
      "start": "2026-06-30T09:00:00Z",
      "player1": "Leolia Jeanjean",
      "player2": "Veronika Erjavec",
      "odds1": 1.61,
      "odds2": 2.39,
      "prob1": "0.5975",
      "prob2": "0.4025",
      "bookmaker": "Pinnacle",
      "sport_key": "tennis_wta_wimbledon",
      "region": "eu"
    },
    {
      "event_id": "648cb18ce359450c85a364ba4d389935",
      "start": "2026-06-30T09:00:00Z",
      "player1": "Liudmila Samsonova",
      "player2": "Polina Kudermetova",
      "odds1": 1.49,
      "odds2": 2.74,
      "prob1": "0.6478",
      "prob2": "0.3522",
      "bookmaker": "Pinnacle",
      "sport_key": "tennis_wta_wimbledon",
      "region": "eu"
    },
    {
      "event_id": "abbf958d2c95704fd6f6cc396b015bff",
      "start": "2026-06-30T09:00:00Z",
      "player1": "Maria Camila Osorio Serrano",
      "player2": "Simona Waltert",
      "odds1": 1.52,
      "odds2": 2.63,
      "prob1": "0.6337",
      "prob2": "0.3663",
      "bookmaker": "Pinnacle",
      "sport_key": "tennis_wta_wimbledon",
      "region": "eu"
    },
    {
      "event_id": "373a68b16637c7b2156b55f1b3824b0c",
      "start": "2026-06-30T09:00:00Z",
      "player1": "Marie Bouzkova",
      "player2": "Talia Gibson",
      "odds1": 1.35,
      "odds2": 3.38,
      "prob1": "0.7146",
      "prob2": "0.2854",
      "bookmaker": "Pinnacle",
      "sport_key": "tennis_wta_wimbledon",
      "region": "eu"
    },
    {
      "event_id": "afe1b515efa9da4c9497f95d6e66505e",
      "start": "2026-06-30T09:00:00Z",
      "player1": "Maya Joint",
      "player2": "Serena Williams",
      "odds1": 1.69,
      "odds2": 2.24,
      "prob1": "0.5700",
      "prob2": "0.4300",
      "bookmaker": "Pinnacle",
      "sport_key": "tennis_wta_wimbledon",
      "region": "eu"
    },
    {
      "event_id": "09517e91efe552b803ef4c28e4683234",
      "start": "2026-06-30T09:00:00Z",
      "player1": "Oksana Selekhmeteva",
      "player2": "Sinja Kraus",
      "odds1": 2.1,
      "odds2": 1.78,
      "prob1": "0.4588",
      "prob2": "0.5412",
      "bookmaker": "Pinnacle",
      "sport_key": "tennis_wta_wimbledon",
      "region": "eu"
    },
    {
      "event_id": "5f14908716f7ada706ceb0b7a7962e8e",
      "start": "2026-06-30T09:00:00Z",
      "player1": "Petra Marcinko",
      "player2": "Sofia Kenin",
      "odds1": 1.71,
      "odds2": 2.2,
      "prob1": "0.5627",
      "prob2": "0.4373",
      "bookmaker": "Pinnacle",
      "sport_key": "tennis_wta_wimbledon",
      "region": "eu"
    },
    {
      "event_id": "778263671cea7a6ce00439628ed04e1c",
      "start": "2026-06-30T09:00:00Z",
      "player1": "Sara Bejlek",
      "player2": "Sorana Cirstea",
      "odds1": 3.21,
      "odds2": 1.38,
      "prob1": "0.3007",
      "prob2": "0.6993",
      "bookmaker": "Pinnacle",
      "sport_key": "tennis_wta_wimbledon",
      "region": "eu"
    },
    {
      "event_id": "4629366ea9fe1ca7987172956e695f80",
      "start": "2026-06-30T10:00:00Z",
      "player1": "Amanda Anisimova",
      "player2": "Lina Gjorcheska",
      "odds1": 1.04,
      "odds2": 11,
      "prob1": "0.9136",
      "prob2": "0.0864",
      "bookmaker": "Winamax (FR)",
      "sport_key": "tennis_wta_wimbledon",
      "region": "eu"
    },
    {
      "event_id": "a1560a72ca3539b3b367dbfd2cf82a20",
      "start": "2026-06-30T10:00:00Z",
      "player1": "Anna Blinkova",
      "player2": "Yuliia Starodubtseva",
      "odds1": 2.24,
      "odds2": 1.69,
      "prob1": "0.4300",
      "prob2": "0.5700",
      "bookmaker": "Pinnacle",
      "sport_key": "tennis_wta_wimbledon",
      "region": "eu"
    },
    {
      "event_id": "2fb7471ab4bcfbda3872e28173b74189",
      "start": "2026-06-30T14:00:00Z",
      "player1": "Elena Rybakina",
      "player2": "Lois Boisson",
      "odds1": 1,
      "odds2": 20,
      "prob1": "0.9524",
      "prob2": "0.0476",
      "bookmaker": "Winamax (FR)",
      "sport_key": "tennis_wta_wimbledon",
      "region": "eu"
    },
    {
      "event_id": "0fb923dd4e2e638f430d3d558d097c53",
      "start": "2026-06-30T16:00:00Z",
      "player1": "Marta Kostyuk",
      "player2": "Nadia Podoroska",
      "odds1": 1,
      "odds2": 16,
      "prob1": "0.9412",
      "prob2": "0.0588",
      "bookmaker": "Winamax (FR)",
      "sport_key": "tennis_wta_wimbledon",
      "region": "eu"
    }
  ]
}