{
  "fetchedAt": "2026-04-22T12:34:51.113Z",
  "region": "eu",
  "count": 60,
  "events": [
    {
      "event_id": "1a99944adbea28dbb517b20fdf4cccf4",
      "start": "2026-04-22T10:30:00Z",
      "player1": "Dino Prizmic",
      "player2": "Matteo Berrettini",
      "odds1": 1.6,
      "odds2": 2.3,
      "prob1": "0.5897",
      "prob2": "0.4103",
      "bookmaker": "Betsson",
      "sport_key": "tennis_atp_madrid_open",
      "region": "eu"
    },
    {
      "event_id": "096f5c6ba1a70f12e2d9eae4776f401b",
      "start": "2026-04-22T10:55:00Z",
      "player1": "Damir Dzumhur",
      "player2": "Mattia Bellucci",
      "odds1": 1.02,
      "odds2": 25,
      "prob1": "0.9608",
      "prob2": "0.0392",
      "bookmaker": "Matchbook",
      "sport_key": "tennis_atp_madrid_open",
      "region": "eu"
    },
    {
      "event_id": "fbeb9fdfc16a623ed040b44d8f53b066",
      "start": "2026-04-22T12:35:00Z",
      "player1": "Dusan Lajovic",
      "player2": "Lorenzo Sonego",
      "odds1": 1.74,
      "odds2": 2.12,
      "prob1": "0.5492",
      "prob2": "0.4508",
      "bookmaker": "1xBet",
      "sport_key": "tennis_atp_madrid_open",
      "region": "eu"
    },
    {
      "event_id": "d9a6355cf04f888a8f435d19b5e082c7",
      "start": "2026-04-22T13:00:00Z",
      "player1": "Alexandre Muller",
      "player2": "Jan-Lennard Struff",
      "odds1": 1.53,
      "odds2": 2.5,
      "prob1": "0.6203",
      "prob2": "0.3797",
      "bookmaker": "Matchbook",
      "sport_key": "tennis_atp_madrid_open",
      "region": "eu"
    },
    {
      "event_id": "0ae371afc9a738681b0aab98491d6f2c",
      "start": "2026-04-22T13:00:00Z",
      "player1": "Roberto Bautista Agut",
      "player2": "Thiago Agustin Tirante",
      "odds1": 2.64,
      "odds2": 1.53,
      "prob1": "0.3669",
      "prob2": "0.6331",
      "bookmaker": "1xBet",
      "sport_key": "tennis_atp_madrid_open",
      "region": "eu"
    },
    {
      "event_id": "f859df4936b66688aebf42bc4ffde786",
      "start": "2026-04-22T13:30:00Z",
      "player1": "Elmer Moller",
      "player2": "Federico Coria",
      "odds1": 1.61,
      "odds2": 2.33,
      "prob1": "0.5914",
      "prob2": "0.4086",
      "bookmaker": "Nordic Bet",
      "sport_key": "tennis_atp_madrid_open",
      "region": "eu"
    },
    {
      "event_id": "5273939288e95b597374cc1a9f564ca3",
      "start": "2026-04-22T13:50:00Z",
      "player1": "Nikoloz Basilashvili",
      "player2": "Sebastian Ofner",
      "odds1": 2.45,
      "odds2": 1.61,
      "prob1": "0.3966",
      "prob2": "0.6034",
      "bookmaker": "1xBet",
      "sport_key": "tennis_atp_madrid_open",
      "region": "eu"
    },
    {
      "event_id": "9a0ee03d877e66062a1084da48139bf1",
      "start": "2026-04-22T14:00:00Z",
      "player1": "Hubert Hurkacz",
      "player2": "Jaime Faria",
      "odds1": 1.36,
      "odds2": 3.15,
      "prob1": "0.6984",
      "prob2": "0.3016",
      "bookmaker": "Nordic Bet",
      "sport_key": "tennis_atp_madrid_open",
      "region": "eu"
    },
    {
      "event_id": "bada98d7acbba2f1d95a3845b42ace91",
      "start": "2026-04-22T14:15:00Z",
      "player1": "Benjamin Bonzi",
      "player2": "Titouan Droguet",
      "odds1": 2.15,
      "odds2": 1.7,
      "prob1": "0.4416",
      "prob2": "0.5584",
      "bookmaker": "Unibet (FR)",
      "sport_key": "tennis_atp_madrid_open",
      "region": "eu"
    },
    {
      "event_id": "a35b0b529fa9f0864e8ceda679391cf1",
      "start": "2026-04-22T14:25:00Z",
      "player1": "Francisco Comesana",
      "player2": "Tomas Machac",
      "odds1": 2.76,
      "odds2": 1.49,
      "prob1": "0.3506",
      "prob2": "0.6494",
      "bookmaker": "1xBet",
      "sport_key": "tennis_atp_madrid_open",
      "region": "eu"
    },
    {
      "event_id": "1252bffae6316daa093b3012e10496ce",
      "start": "2026-04-22T15:55:00Z",
      "player1": "Alejandro Tabilo",
      "player2": "Valentin Royer",
      "odds1": 1.4,
      "odds2": 3.15,
      "prob1": "0.6923",
      "prob2": "0.3077",
      "bookmaker": "1xBet",
      "sport_key": "tennis_atp_madrid_open",
      "region": "eu"
    },
    {
      "event_id": "e2d10f7396e7de14ff8eca476dbd3ae5",
      "start": "2026-04-22T16:30:00Z",
      "player1": "Jesper De Jong",
      "player2": "Rafael Jodar",
      "odds1": 5.35,
      "odds2": 1.19,
      "prob1": "0.1820",
      "prob2": "0.8180",
      "bookmaker": "1xBet",
      "sport_key": "tennis_atp_madrid_open",
      "region": "eu"
    },
    {
      "event_id": "490684d4d74adbab5fc0a905d8b3deef",
      "start": "2026-04-23T08:00:00Z",
      "player1": "Adolfo Daniel Vallejo",
      "player2": "Grigor Dimitrov",
      "odds1": 1.91,
      "odds2": 2.02,
      "prob1": "0.5140",
      "prob2": "0.4860",
      "bookmaker": "Matchbook",
      "sport_key": "tennis_atp_madrid_open",
      "region": "eu"
    },
    {
      "event_id": "26b14d53b079528c898d0e70ddd0a9af",
      "start": "2026-04-23T08:00:00Z",
      "player1": "Alexei Popyrin",
      "player2": "Martin Damm Jr.",
      "odds1": 1.45,
      "odds2": 2.81,
      "prob1": "0.6596",
      "prob2": "0.3404",
      "bookmaker": "GTbets",
      "sport_key": "tennis_atp_madrid_open",
      "region": "eu"
    },
    {
      "event_id": "701a036b37a3c32991169ec60f217614",
      "start": "2026-04-23T08:00:00Z",
      "player1": "Andrey Rublev",
      "player2": "Vit Kopriva",
      "odds1": 1.24,
      "odds2": 4.4,
      "prob1": "0.7801",
      "prob2": "0.2199",
      "bookmaker": "1xBet",
      "sport_key": "tennis_atp_madrid_open",
      "region": "eu"
    },
    {
      "event_id": "a399fc935e26c30dcef58389ed1a2f7a",
      "start": "2026-04-23T08:00:00Z",
      "player1": "Arthur Fils",
      "player2": "Ignacio Buse",
      "odds1": 1.09,
      "odds2": 5.63,
      "prob1": "0.8378",
      "prob2": "0.1622",
      "bookmaker": "1xBet",
      "sport_key": "tennis_atp_madrid_open",
      "region": "eu"
    },
    {
      "event_id": "ba3b62e957d4817f64b0326abbe465ea",
      "start": "2026-04-23T08:00:00Z",
      "player1": "Emilio Nava",
      "player2": "Valentin Vacherot",
      "odds1": 3.05,
      "odds2": 1.42,
      "prob1": "0.3177",
      "prob2": "0.6823",
      "bookmaker": "1xBet",
      "sport_key": "tennis_atp_madrid_open",
      "region": "eu"
    },
    {
      "event_id": "4e286acc07f3c6ca06060986d01e80d7",
      "start": "2026-04-23T08:00:00Z",
      "player1": "Joao Fonseca",
      "player2": "Marin Cilic",
      "odds1": 1.3,
      "odds2": 3.85,
      "prob1": "0.7476",
      "prob2": "0.2524",
      "bookmaker": "1xBet",
      "sport_key": "tennis_atp_madrid_open",
      "region": "eu"
    },
    {
      "event_id": "b50ef040e5a29090d772d6010242c44d",
      "start": "2026-04-23T08:00:00Z",
      "player1": "Nicolai Budkov Kjaer",
      "player2": "Reilly Opelka",
      "odds1": 2.05,
      "odds2": 1.78,
      "prob1": "0.4648",
      "prob2": "0.5352",
      "bookmaker": "GTbets",
      "sport_key": "tennis_atp_madrid_open",
      "region": "eu"
    },
    {
      "event_id": "ef90207216259d42de19ed123bb16cc5",
      "start": "2026-04-23T08:00:00Z",
      "player1": "Patrick Kypson",
      "player2": "Stefanos Tsitsipas",
      "odds1": 3,
      "odds2": 1.33,
      "prob1": "0.3072",
      "prob2": "0.6928",
      "bookmaker": "Unibet (FR)",
      "sport_key": "tennis_atp_madrid_open",
      "region": "eu"
    },
    {
      "event_id": "287506c21474518ef36a0be239f29864",
      "start": "2026-04-23T08:00:00Z",
      "player1": "Sebastian Baez",
      "player2": "Vilius Gaubas",
      "odds1": 1.39,
      "odds2": 2.93,
      "prob1": "0.6782",
      "prob2": "0.3218",
      "bookmaker": "GTbets",
      "sport_key": "tennis_atp_madrid_open",
      "region": "eu"
    },
    {
      "event_id": "633b185bb2d2390d7af7df84bd7504ce",
      "start": "2026-04-23T09:00:00Z",
      "player1": "Adam Walton",
      "player2": "Martin Landaluce",
      "odds1": 4.17,
      "odds2": 1.26,
      "prob1": "0.2320",
      "prob2": "0.7680",
      "bookmaker": "1xBet",
      "sport_key": "tennis_atp_madrid_open",
      "region": "eu"
    },
    {
      "event_id": "e508264003381138d77c8a1826151e7e",
      "start": "2026-04-23T09:00:00Z",
      "player1": "Alexander Blockx",
      "player2": "Botic van de Zandschulp",
      "odds1": 1.68,
      "odds2": 2.3,
      "prob1": "0.5779",
      "prob2": "0.4221",
      "bookmaker": "1xBet",
      "sport_key": "tennis_atp_madrid_open",
      "region": "eu"
    },
    {
      "event_id": "7356c66507a41acf91db5b53af57ae92",
      "start": "2026-04-23T09:00:00Z",
      "player1": "Alexander Shevchenko",
      "player2": "Jaume Munar",
      "odds1": 2.45,
      "odds2": 1.61,
      "prob1": "0.3966",
      "prob2": "0.6034",
      "bookmaker": "1xBet",
      "sport_key": "tennis_atp_madrid_open",
      "region": "eu"
    },
    {
      "event_id": "2b190b89a40eec01e0a5a32b1b754852",
      "start": "2026-04-23T09:00:00Z",
      "player1": "Camilo Ugo Carabelli",
      "player2": "Gael Monfils",
      "odds1": 1.61,
      "odds2": 2.45,
      "prob1": "0.6034",
      "prob2": "0.3966",
      "bookmaker": "1xBet",
      "sport_key": "tennis_atp_madrid_open",
      "region": "eu"
    },
    {
      "event_id": "c561b1df65bf6ff58d6b360f2d4037f8",
      "start": "2026-04-23T09:00:00Z",
      "player1": "Daniel Altmaier",
      "player2": "Juan Manuel Cerundolo",
      "odds1": 2.2,
      "odds2": 1.74,
      "prob1": "0.4416",
      "prob2": "0.5584",
      "bookmaker": "1xBet",
      "sport_key": "tennis_atp_madrid_open",
      "region": "eu"
    },
    {
      "event_id": "f2f6623f881276b52055f468b20bb282",
      "start": "2026-04-23T09:00:00Z",
      "player1": "Ethan Quinn",
      "player2": "Fabian Marozsan",
      "odds1": 2.16,
      "odds2": 1.76,
      "prob1": "0.4490",
      "prob2": "0.5510",
      "bookmaker": "1xBet",
      "sport_key": "tennis_atp_madrid_open",
      "region": "eu"
    },
    {
      "event_id": "846b763871a4578e1a68a45625d3ae70",
      "start": "2026-04-23T09:00:00Z",
      "player1": "Marcos Giron",
      "player2": "Yannick Hanfmann",
      "odds1": 3.1,
      "odds2": 1.41,
      "prob1": "0.3126",
      "prob2": "0.6874",
      "bookmaker": "1xBet",
      "sport_key": "tennis_atp_madrid_open",
      "region": "eu"
    },
    {
      "event_id": "38f21f30c7bb61312d7eab9884f91e55",
      "start": "2026-04-23T09:00:00Z",
      "player1": "Mariano Navone",
      "player2": "Nuno Borges",
      "odds1": 1.59,
      "odds2": 2.5,
      "prob1": "0.6112",
      "prob2": "0.3888",
      "bookmaker": "1xBet",
      "sport_key": "tennis_atp_madrid_open",
      "region": "eu"
    },
    {
      "event_id": "c99aa3867587d99a82ee100dc6c01b61",
      "start": "2026-04-23T09:00:00Z",
      "player1": "Marton Fucsovics",
      "player2": "Pablo Carreno Busta",
      "odds1": 1.97,
      "odds2": 1.91,
      "prob1": "0.4923",
      "prob2": "0.5077",
      "bookmaker": "1xBet",
      "sport_key": "tennis_atp_madrid_open",
      "region": "eu"
    },
    {
      "event_id": "8f7518f8cf8322817e0ef97934b40846",
      "start": "2026-04-23T09:00:00Z",
      "player1": "Miomir Kecmanovic",
      "player2": "Terence Atmane",
      "odds1": 1.68,
      "odds2": 2.3,
      "prob1": "0.5779",
      "prob2": "0.4221",
      "bookmaker": "1xBet",
      "sport_key": "tennis_atp_madrid_open",
      "region": "eu"
    },
    {
      "event_id": "b11e371cab5b3b2b5cca5d8fae8a5f5c",
      "start": "2026-04-23T13:40:00Z",
      "player1": "Daniel Merida Aguilar",
      "player2": "Marco Trungelliti",
      "odds1": 1.75,
      "odds2": 2.16,
      "prob1": "0.5524",
      "prob2": "0.4476",
      "bookmaker": "Pinnacle",
      "sport_key": "tennis_atp_madrid_open",
      "region": "eu"
    },
    {
      "event_id": "c19400b5186b61499ea2cd2abc4ef2a9",
      "start": "2026-04-22T10:56:00Z",
      "player1": "Daria Kasatkina",
      "player2": "Daria Snigur",
      "odds1": 1.76,
      "odds2": 2.3,
      "prob1": "0.5665",
      "prob2": "0.4335",
      "bookmaker": "Betfair",
      "sport_key": "tennis_wta_madrid_open",
      "region": "eu"
    },
    {
      "event_id": "6ba23d1ed2d366915ccbf56730d000a2",
      "start": "2026-04-22T11:00:00Z",
      "player1": "Moyuka Uchijima",
      "player2": "Yuliia Starodubtseva",
      "odds1": 3.6,
      "odds2": 1.36,
      "prob1": "0.2742",
      "prob2": "0.7258",
      "bookmaker": "Betfair",
      "sport_key": "tennis_wta_madrid_open",
      "region": "eu"
    },
    {
      "event_id": "773b42a98159a273e7385a82636d834e",
      "start": "2026-04-22T11:21:00Z",
      "player1": "Ajla Tomljanovic",
      "player2": "Dalma Galfi",
      "odds1": 3.45,
      "odds2": 1.35,
      "prob1": "0.2813",
      "prob2": "0.7188",
      "bookmaker": "Betfair",
      "sport_key": "tennis_wta_madrid_open",
      "region": "eu"
    },
    {
      "event_id": "666e0f260272f0ff2a99665baca46f1f",
      "start": "2026-04-22T11:30:00Z",
      "player1": "Alycia Parks",
      "player2": "Elisabetta Cocciaretto",
      "odds1": 1.15,
      "odds2": 7.2,
      "prob1": "0.8623",
      "prob2": "0.1377",
      "bookmaker": "Betfair",
      "sport_key": "tennis_wta_madrid_open",
      "region": "eu"
    },
    {
      "event_id": "49229c92223ae3400d3a06696ab45417",
      "start": "2026-04-22T11:41:00Z",
      "player1": "Alexandra Eala",
      "player2": "Anastasia Pavlyuchenkova",
      "odds1": 1.12,
      "odds2": 5.6,
      "prob1": "0.8333",
      "prob2": "0.1667",
      "bookmaker": "Betsson",
      "sport_key": "tennis_wta_madrid_open",
      "region": "eu"
    },
    {
      "event_id": "1f5b6a8de5b8ef555a3fb931cfb749c7",
      "start": "2026-04-22T12:50:00Z",
      "player1": "Alina Charaeva",
      "player2": "Janice Tjen",
      "odds1": 1.81,
      "odds2": 2.01,
      "prob1": "0.5262",
      "prob2": "0.4738",
      "bookmaker": "Betsson",
      "sport_key": "tennis_wta_madrid_open",
      "region": "eu"
    },
    {
      "event_id": "deacf8a59a90a24743406678a47e3c23",
      "start": "2026-04-22T13:00:00Z",
      "player1": "Anhelina Kalinina",
      "player2": "Kamilla Rakhimova",
      "odds1": 1.49,
      "odds2": 2.65,
      "prob1": "0.6401",
      "prob2": "0.3599",
      "bookmaker": "Betsson",
      "sport_key": "tennis_wta_madrid_open",
      "region": "eu"
    },
    {
      "event_id": "4dd00cef255e458f31b6bec10591045e",
      "start": "2026-04-22T13:00:00Z",
      "player1": "Dayana Yastremska",
      "player2": "Solana Sierra",
      "odds1": 1.3,
      "odds2": 3.5,
      "prob1": "0.7292",
      "prob2": "0.2708",
      "bookmaker": "888sport",
      "sport_key": "tennis_wta_madrid_open",
      "region": "eu"
    },
    {
      "event_id": "6e42ac70128a2eb239b924dff3257264",
      "start": "2026-04-22T13:00:00Z",
      "player1": "Emiliana Arango",
      "player2": "Talia Gibson",
      "odds1": 2.03,
      "odds2": 1.86,
      "prob1": "0.4781",
      "prob2": "0.5219",
      "bookmaker": "Pinnacle",
      "sport_key": "tennis_wta_madrid_open",
      "region": "eu"
    },
    {
      "event_id": "b6ac9d265b70b88fbe5b6ac4b081f00a",
      "start": "2026-04-22T13:00:00Z",
      "player1": "Tereza Valentova",
      "player2": "Yulia Putintseva",
      "odds1": 1.62,
      "odds2": 2.23,
      "prob1": "0.5792",
      "prob2": "0.4208",
      "bookmaker": "GTbets",
      "sport_key": "tennis_wta_madrid_open",
      "region": "eu"
    },
    {
      "event_id": "baef6b6226111e72da3790ad4c36f7a6",
      "start": "2026-04-22T14:20:00Z",
      "player1": "Oleksandra Oliynykova",
      "player2": "Simona Waltert",
      "odds1": 1.96,
      "odds2": 2.02,
      "prob1": "0.5075",
      "prob2": "0.4925",
      "bookmaker": "Betfair",
      "sport_key": "tennis_wta_madrid_open",
      "region": "eu"
    },
    {
      "event_id": "80a229bbec3d962bce124f22cdb0ade2",
      "start": "2026-04-22T14:30:00Z",
      "player1": "Leolia Jeanjean",
      "player2": "Oksana Selekhmeteva",
      "odds1": 2.46,
      "odds2": 1.63,
      "prob1": "0.3985",
      "prob2": "0.6015",
      "bookmaker": "Betfair",
      "sport_key": "tennis_wta_madrid_open",
      "region": "eu"
    },
    {
      "event_id": "49c7e77ae175bf4f009de9260705f421",
      "start": "2026-04-22T15:00:00Z",
      "player1": "Ashlyn Krueger",
      "player2": "Sofia Kenin",
      "odds1": 1.8,
      "odds2": 2.02,
      "prob1": "0.5288",
      "prob2": "0.4712",
      "bookmaker": "Nordic Bet",
      "sport_key": "tennis_wta_madrid_open",
      "region": "eu"
    },
    {
      "event_id": "bc81628a2fcc83dd1251e616f0259e6c",
      "start": "2026-04-22T15:00:00Z",
      "player1": "Karolina Pliskova",
      "player2": "Sinja Kraus",
      "odds1": 1.89,
      "odds2": 2.04,
      "prob1": "0.5191",
      "prob2": "0.4809",
      "bookmaker": "Betfair",
      "sport_key": "tennis_wta_madrid_open",
      "region": "eu"
    },
    {
      "event_id": "77ea81df9f2997ffa2d7e002db1db2ec",
      "start": "2026-04-22T15:30:00Z",
      "player1": "Katie Boulter",
      "player2": "Taylor Townsend",
      "odds1": 1.98,
      "odds2": 1.84,
      "prob1": "0.4817",
      "prob2": "0.5183",
      "bookmaker": "Betsson",
      "sport_key": "tennis_wta_madrid_open",
      "region": "eu"
    },
    {
      "event_id": "f9400367155e754e3290fa678b1a9352",
      "start": "2026-04-22T15:45:00Z",
      "player1": "Caty McNally",
      "player2": "Katie Volynets",
      "odds1": 1.76,
      "odds2": 2.22,
      "prob1": "0.5578",
      "prob2": "0.4422",
      "bookmaker": "Betfair",
      "sport_key": "tennis_wta_madrid_open",
      "region": "eu"
    },
    {
      "event_id": "7d014abf7d93e3b44a9bffe68c139bbf",
      "start": "2026-04-22T15:50:00Z",
      "player1": "Elvina Kalieva",
      "player2": "Katerina Siniakova",
      "odds1": 2.8,
      "odds2": 1.45,
      "prob1": "0.3412",
      "prob2": "0.6588",
      "bookmaker": "Betsson",
      "sport_key": "tennis_wta_madrid_open",
      "region": "eu"
    },
    {
      "event_id": "03836947724778e4b53a0ede239327a2",
      "start": "2026-04-22T16:00:00Z",
      "player1": "Elsa Jacquemot",
      "player2": "Tyra Caterina Grant",
      "odds1": 2.34,
      "odds2": 1.72,
      "prob1": "0.4236",
      "prob2": "0.5764",
      "bookmaker": "Betfair",
      "sport_key": "tennis_wta_madrid_open",
      "region": "eu"
    },
    {
      "event_id": "2a46465fc04590e4b38cd649a97d8732",
      "start": "2026-04-23T12:00:00Z",
      "player1": "Anna Bondár",
      "player2": "Elina Svitolina",
      "odds1": 5.8,
      "odds2": 1.18,
      "prob1": "0.1691",
      "prob2": "0.8309",
      "bookmaker": "Betfair",
      "sport_key": "tennis_wta_madrid_open",
      "region": "eu"
    },
    {
      "event_id": "a4b1b15fd84fc2be1b7c9c6dc556c206",
      "start": "2026-04-23T12:00:00Z",
      "player1": "Aryna Sabalenka",
      "player2": "Peyton Stearns",
      "odds1": 1.05,
      "odds2": 17.5,
      "prob1": "0.9434",
      "prob2": "0.0566",
      "bookmaker": "Betfair",
      "sport_key": "tennis_wta_madrid_open",
      "region": "eu"
    },
    {
      "event_id": "8a31cab8ce11c8f5d7098ec705fbf191",
      "start": "2026-04-23T12:00:00Z",
      "player1": "Belinda Bencic",
      "player2": "Petra Marcinko",
      "odds1": 1.2,
      "odds2": 5.3,
      "prob1": "0.8154",
      "prob2": "0.1846",
      "bookmaker": "Betfair",
      "sport_key": "tennis_wta_madrid_open",
      "region": "eu"
    },
    {
      "event_id": "03c7010ccadd6ed325cdc47f71dbeee0",
      "start": "2026-04-23T12:00:00Z",
      "player1": "Diana Shnaider",
      "player2": "Jessica Bouzas Maneiro",
      "odds1": 1.35,
      "odds2": 3.6,
      "prob1": "0.7273",
      "prob2": "0.2727",
      "bookmaker": "Betfair",
      "sport_key": "tennis_wta_madrid_open",
      "region": "eu"
    },
    {
      "event_id": "59534a87349c90090b7266e13eaeaaf1",
      "start": "2026-04-23T12:00:00Z",
      "player1": "Hailey Baptiste",
      "player2": "Kaitlin Quevedo",
      "odds1": 1.44,
      "odds2": 2.96,
      "prob1": "0.6727",
      "prob2": "0.3273",
      "bookmaker": "1xBet",
      "sport_key": "tennis_wta_madrid_open",
      "region": "eu"
    },
    {
      "event_id": "8cb637ea6fadd754c11b3e2bc48dc18f",
      "start": "2026-04-23T12:00:00Z",
      "player1": "Iva Jović",
      "player2": "Magda Linette",
      "odds1": 1.51,
      "odds2": 2.78,
      "prob1": "0.6480",
      "prob2": "0.3520",
      "bookmaker": "Betfair",
      "sport_key": "tennis_wta_madrid_open",
      "region": "eu"
    },
    {
      "event_id": "5f2c608a517eee96b6e5b1c89c94cc9d",
      "start": "2026-04-23T12:00:00Z",
      "player1": "Jasmine Paolini",
      "player2": "Laura Siegemund",
      "odds1": 1.33,
      "odds2": 3.7,
      "prob1": "0.7356",
      "prob2": "0.2644",
      "bookmaker": "Betfair",
      "sport_key": "tennis_wta_madrid_open",
      "region": "eu"
    },
    {
      "event_id": "e231db1bedd59f19be92fcda1e84e2fe",
      "start": "2026-04-23T12:00:00Z",
      "player1": "Julia Grabher",
      "player2": "Leylah Fernandez",
      "odds1": 5.6,
      "odds2": 1.18,
      "prob1": "0.1740",
      "prob2": "0.8260",
      "bookmaker": "Betfair",
      "sport_key": "tennis_wta_madrid_open",
      "region": "eu"
    },
    {
      "event_id": "291ec84c0d6da22f5922bf7fee020391",
      "start": "2026-04-23T12:00:00Z",
      "player1": "Laura Samson",
      "player2": "Xinyu Wang",
      "odds1": 2.1,
      "odds2": 1.81,
      "prob1": "0.4629",
      "prob2": "0.5371",
      "bookmaker": "Betfair",
      "sport_key": "tennis_wta_madrid_open",
      "region": "eu"
    },
    {
      "event_id": "418ceda4e36c4d64c5bc213decd11e04",
      "start": "2026-04-23T12:00:00Z",
      "player1": "Maria Camila Osorio Serrano",
      "player2": "Naomi Osaka",
      "odds1": 1.95,
      "odds2": 1.94,
      "prob1": "0.4987",
      "prob2": "0.5013",
      "bookmaker": "Betfair",
      "sport_key": "tennis_wta_madrid_open",
      "region": "eu"
    }
  ]
}